clibsorts/measurements.c
clibsorts/plotting_controls.c
clibsorts/radar.c
clibsorts/radar_controller.c
clibsorts/signals.c
clibsorts/static_priority_scheduler.c
sorts/__init__.py
sorts/const.py
sorts/constants.py
sorts/correlator.py
sorts/dates.py
sorts/frames.py
sorts/functions.py
sorts/interpolation.py
sorts/logging.py
sorts/logging_test.py
sorts/mpi_queued_execution.py
sorts/passes.py
sorts/pre_encounter.py
sorts/py.typed
sorts/signals.py
sorts/simulation_v1.py
sorts/space_object.py
sorts/types.py
sorts/utils.py
sorts/version.py
sorts/cli/__init__.py
sorts/cli/commands.py
sorts/cli/discos_download.py
sorts/cli/spacetrack_download.py
sorts/controller/__init__.py
sorts/controller/controller_base.py
sorts/controller/fence_scan_controller.py
sorts/controller/pointing_funcs.py
sorts/controller/sparse_tracker_controller.py
sorts/controller/tracker_controller.py
sorts/controller_v1/__init__.py
sorts/controller_v1/radar_controller.py
sorts/controller_v1/scanner.py
sorts/controller_v1/static.py
sorts/controller_v1/tracker.py
sorts/data/MCerr_n10_tx1920_ipp10000_bw100000.h5
sorts/data/__init__.py
sorts/data/ndmxml-2.0.0-aem-1.0.xsd
sorts/data/ndmxml-2.0.0-apm-1.0.xsd
sorts/data/ndmxml-2.0.0-cdm-1.0.xsd
sorts/data/ndmxml-2.0.0-common-2.0.xsd
sorts/data/ndmxml-2.0.0-master-2.0.xsd
sorts/data/ndmxml-2.0.0-namespace-2.0.xsd
sorts/data/ndmxml-2.0.0-ndm-2.0.xsd
sorts/data/ndmxml-2.0.0-oem-2.0.xsd
sorts/data/ndmxml-2.0.0-omm-2.0.xsd
sorts/data/ndmxml-2.0.0-opm-2.0.xsd
sorts/data/ndmxml-2.0.0-rdm-1.0.xsd
sorts/data/ndmxml-2.0.0-tdm-2.0.xsd
sorts/errors/__init__.py
sorts/errors/atmospheric_drag.py
sorts/errors/errors.py
sorts/errors/ionospheric_ray_trace.py
sorts/errors/linearized_coded.py
sorts/errors/linearized_orbit_determination.py
sorts/io/__init__.py
sorts/io/ccsds.py
sorts/io/terminal.py
sorts/plots/__init__.py
sorts/plots/azel_skyplot.py
sorts/plots/ecef_states_positions_plot.py
sorts/plots/kepler_space_object_on_map.py
sorts/plots/radar_schedule_ecef_position_plot.py
sorts-5.0.0rc1.dist-info/licenses/LICENSE
sorts-5.0.0rc1.dist-info/METADATA
sorts-5.0.0rc1.dist-info/WHEEL
sorts-5.0.0rc1.dist-info/top_level.txt
sorts-5.0.0rc1.dist-info/RECORD
