Metadata-Version: 2.4
Name: sorts
Version: 5.0.0rc1
Summary: Space Object Radar Tracking Simulator
Author: Tsz-Hin Heung, Juha Vierinen
Author-email: Daniel Kastinen <daniel.kastinen@irf.se>
Maintainer-email: Daniel Kastinen <daniel.kastinen@irf.se>
License: MIT License
Project-URL: Documentation, https://danielk.developer.irf.se/sorts/
Project-URL: Repository, https://github.com/danielk333/sorts
Classifier: Intended Audience :: Science/Research
Classifier: Programming Language :: Python :: 3
Classifier: Topic :: Scientific/Engineering :: Physics
Classifier: Operating System :: Unix
Requires-Python: >=3.12
License-File: LICENSE
Requires-Dist: h5py>=3.2.1
Requires-Dist: matplotlib>=2.2.2
Requires-Dist: numpy>=1.14.3
Requires-Dist: scipy>=1.1.0
Requires-Dist: sgp4>=2.7
Requires-Dist: tabulate>=0.8.7
Requires-Dist: tqdm>=4.46.0
Requires-Dist: astropy>=4.1
Requires-Dist: xmlschema>=1.5.1
Requires-Dist: pyorb>=0.5.4
Requires-Dist: pyant>=1.1
Requires-Dist: yappi>=1.4.0
Requires-Dist: requests>=2.32.3
Requires-Dist: pandas>=2.2.3
Requires-Dist: pyqt6>=6.8.1
Requires-Dist: bokeh>=3.7.3
Requires-Dist: jupyter-bokeh>=4.0.5
Requires-Dist: jupyterlab>=4.4.4
Requires-Dist: lets-plot>=4.6.2
Requires-Dist: panel>=1.7.4
Requires-Dist: pyproj>=3.7.1
Requires-Dist: pyvista>=0.45.2
Requires-Dist: xarray>=2025.8.0
Requires-Dist: bottleneck>=1.5.0
Requires-Dist: mpi4py>=4.1.0
Requires-Dist: h5netcdf>=1.6.4
Provides-Extra: spacetrack
Requires-Dist: spacetrack>=1.0.1; extra == "spacetrack"
Provides-Extra: jupyter
Requires-Dist: ipykernel>=6.29.5; extra == "jupyter"
Requires-Dist: ipywidgets>=8.1.7; extra == "jupyter"
Requires-Dist: jupyter-bokeh>=4.0.5; extra == "jupyter"
Requires-Dist: jupyterlab>=4.4.4; extra == "jupyter"
Provides-Extra: dev
Requires-Dist: pytest>=6.2.5; extra == "dev"
Requires-Dist: flake8>=4.0.1; extra == "dev"
Requires-Dist: wheel>=0.37.0; extra == "dev"
Requires-Dist: build>=0.7.0; extra == "dev"
Requires-Dist: twine>=3.4.2; extra == "dev"
Requires-Dist: pytest-cov>=4.1.0; extra == "dev"
Requires-Dist: matplotlib>=3.5.1; extra == "dev"
Requires-Dist: ipykernel>=6.9.1; extra == "dev"
Requires-Dist: radon>=5.1.0; extra == "dev"
Requires-Dist: numpydoc>=1.2; extra == "dev"
Requires-Dist: pre-commit>3.0.0; extra == "dev"
Requires-Dist: black>=23.3.0; extra == "dev"
Requires-Dist: auditwheel>=5.4.0; extra == "dev"
Requires-Dist: patchelf>=0.14; extra == "dev"
Requires-Dist: watchfiles>=1.1.0; extra == "dev"
Requires-Dist: mkdocs>=1.6.1; extra == "dev"
Requires-Dist: mkdocs-gen-files>=0.5.0; extra == "dev"
Requires-Dist: mkdocstrings[python]>=0.30.0; extra == "dev"
Requires-Dist: mkdocs-section-index>=0.3.10; extra == "dev"
Requires-Dist: mkdocs-literate-nav>=0.6.2; extra == "dev"
Requires-Dist: jupytext>=1.17.2; extra == "dev"
Requires-Dist: mkdocs-jupyter>=0.25.1; extra == "dev"
Dynamic: license-file
